task1/rom.sv
module rom #( //# allows for parameterisation so later you can do rom #(ADDRESS_WIDTH=16, DA...=10) (...)
    parameter   ADDRESS_WIDTH = 8,
                DATA_WIDTH = 8
)(
    input logic                         clk,
    input logic     [ADDRESS_WIDTH-1:0] addr,
    output logic    [DATA_WIDTH-1:0]    dout
);

logic [DATA_WIDTH-1:0] rom_array [2**ADDRESS_WIDTH-1:0]; //rom_array is an internal value that has memory

initial begin //initial means initialise. Usually non-synthesisable commands (e.g. wouldn't synthesise readmemh, as rom would be built with it)
        $display("Loading rom.");
        //This sort of stuff wouldn't work when programming for an actual chip (other than FPGA, which has data stream)
        $readmemh("sinerom.mem", rom_array);
        //can find more of these macros 
end;

always_ff @(posedge clk)
    dout <= rom_array[addr];

endmodule

task1/counter.sv
module counter #(
    parameter WIDTH = 8
)(
    // interface signals
    input   logic               clk,    // clock
    input   logic               rst,    // reset
    input   logic               en,
    input   logic [WIDTH-1:0]   incr,
    output  logic [WIDTH-1:0]   count   // count output 
);

always_ff @ (posedge clk) //this specifies a clocked circuit. posedge rst is async reset.
    if(rst) count <= {WIDTH{1'b0}}; //Uses concatenation operator
    else if(en)    count <= count + incr;

endmodule

task1/sinegen.sv
module sinegen #(
    parameter   A_WIDTH = 8,
                D_WIDTH = 8
)(
    //interface signals
    input   logic               clk,
    input   logic               rst,
    input   logic               en,
    input   logic [D_WIDTH-1:0] incr,
    output  logic [D_WIDTH-1:0] dout
);

    logic   [A_WIDTH-1:0]       address;    //interconnect wire

counter addrCounter (
    .clk (clk), //These are assigning the values from the module to this module
    .rst (rst),
    .en (en),
    .incr (incr),
    .count (address)
);

rom sineRom (
    .clk (clk),
    .addr (address),
    .dout (dout)
);

endmodule

task1/sinegen.vcd
$version Generated by VerilatedVcd $end
$date Thu Nov  3 15:48:30 2022 $end
$timescale 1ps $end

 $scope module TOP $end
  $var wire  1 # clk $end
  $var wire  8 ' dout [7:0] $end
  $var wire  1 % en $end
  $var wire  8 & incr [7:0] $end
  $var wire  1 $ rst $end
  $scope module sinegen $end
   $var wire 32 ) A_WIDTH [31:0] $end
   $var wire 32 ) D_WIDTH [31:0] $end
   $var wire  8 ( address [7:0] $end
   $var wire  1 # clk $end
   $var wire  8 ' dout [7:0] $end
   $var wire  1 % en $end
   $var wire  8 & incr [7:0] $end
   $var wire  1 $ rst $end
   $scope module addrCounter $end
    $var wire 32 ) WIDTH [31:0] $end
    $var wire  1 # clk $end
    $var wire  8 ( count [7:0] $end
    $var wire  1 % en $end
    $var wire  8 & incr [7:0] $end
    $var wire  1 $ rst $end
   $upscope $end
   $scope module sineRom $end
    $var wire 32 ) ADDRESS_WIDTH [31:0] $end
    $var wire 32 ) DATA_WIDTH [31:0] $end
    $var wire  8 ( addr [7:0] $end
    $var wire  1 # clk $end
    $var wire  8 ' dout [7:0] $end
   $upscope $end
  $upscope $end
 $upscope $end
$enddefinitions $end


#0
0#
1$
0%
b00000000 &
b00000000 '
b00000000 (
b00000000000000000000000000001000 )
#2
1#
b00110011 &
b11111110 '
#4
#6
#8
0$
#10
#12
#14
1%
b00110011 (
#16
b10100110 '
b01100110 (
#18
b00011000 '
b10011001 (
#20
b00010111 '
b11001100 (
#22
b10100011 '
b11111111 (
#24
b11111101 '
b00110010 (
#26
b10101001 '
b01100101 (
#28
b00011010 '
b10011000 (
#30
b00010101 '
b11001011 (
#32
b10100000 '
b11111110 (
#34
b11111101 '
b00110001 (
#36
b10101100 '
b01100100 (
#38
b00011100 '
b10010111 (
#40
b00010011 '
b11001010 (
#42
b10011101 '
b11111101 (
#44
b11111101 '
b00110000 (
#46
b10101111 '
b01100011 (
#48
b00011110 '
b10010110 (
#50
b00010010 '
b11001001 (
#52
b10011010 '
b11111100 (
#54
b11111101 '
b00101111 (
#56
b10110010 '
b01100010 (
#58
b00100000 '
b10010101 (
#60
b00010000 '
b11001000 (
#62
b10010111 '
b11111011 (
#64
b11111101 '
b00101110 (
#66
b10110101 '
b01100001 (
#68
b00100011 '
b10010100 (
#70
b00001110 '
b11000111 (
#72
b10010100 '
b11111010 (
#74
b11111100 '
b00101101 (
#76
b10111000 '
b01100000 (
#78
b00100101 '
b10010011 (
#80
b00001101 '
b11000110 (
#82
b10010001 '
b11111001 (
#84
b11111100 '
b00101100 (
#86
b10111010 '
b01011111 (
#88
b00100111 '
b10010010 (
#90
b00001100 '
b11000101 (
#92
b10001110 '
b11111000 (
#94
b11111011 '
b00101011 (
#96
b10111101 '
b01011110 (
#98
b00101001 '
b10010001 (
#100
b00001010 '
b11000100 (
#102
b10001011 '
b11110111 (
#104
b11111010 '
b00101010 (
#106
b11000000 '
b01011101 (
#108
b00101100 '
b10010000 (
#110
b00001001 '
b11000011 (
#112
b10001000 '
b11110110 (
#114
b11111010 '
b00101001 (
#116
b11000010 '
b01011100 (
#118
b00101110 '
b10001111 (
#120
b00001000 '
b11000010 (
#122
b10000101 '
b11110101 (
#124
b11111001 '
b00101000 (
#126
b11000101 '
b01011011 (
#128
b00110000 '
b10001110 (
#130
b00000111 '
b11000001 (
#132
b10000010 '
b11110100 (
#134
b11111000 '
b00100111 (
#136
b11001000 '
b01011010 (
#138
b00110011 '
b10001101 (
#140
b00000110 '
b11000000 (
#142
b01111111 '
b11110011 (
#144
b11110111 '
b00100110 (
#146
b11001010 '
b01011001 (
#148
b00110101 '
b10001100 (
#150
b00000101 '
b10111111 (
#152
b01111011 '
b11110010 (
#154
b11110110 '
b00100101 (
#156
b11001101 '
b01011000 (
#158
b00111000 '
b10001011 (
#160
b00000100 '
b10111110 (
#162
b01111000 '
b11110001 (
#164
b11110101 '
b00100100 (
#166
b11001111 '
b01010111 (
#168
b00111011 '
b10001010 (
#170
b00000011 '
b10111101 (
#172
b01110101 '
b11110000 (
#174
b11110100 '
b00100011 (
#176
b11010001 '
b01010110 (
#178
b00111101 '
b10001001 (
#180
b00000011 '
b10111100 (
#182
b01110010 '
b11101111 (
#184
b11110011 '
b00100010 (
#186
b11010100 '
b01010101 (
#188
b01000000 '
b10001000 (
#190
b00000010 '
b10111011 (
#192
b01101111 '
b11101110 (
#194
b11110001 '
b00100001 (
#196
b11010110 '
b01010100 (
#198
b01000011 '
b10000111 (
#200
b00000001 '
b10111010 (
#202
b01101100 '
b11101101 (
#204
b11110000 '
b00100000 (
#206
b11011000 '
b01010011 (
#208
b01000101 '
b10000110 (
#210
b00000001 '
b10111001 (
#212
b01101001 '
b11101100 (
#214
b11101111 '
b00011111 (
#216
b11011010 '
b01010010 (
#218
b01001000 '
b10000101 (
#220
b00000000 '
b10111000 (
#222
b01100110 '
b11101011 (
#224
b11101101 '
b00011110 (
#226
b11011101 '
b01010001 (
#228
b01001011 '
b10000100 (
#230
b00000000 '
b10110111 (
#232
b01100011 '
b11101010 (
#234
b11101011 '
b00011101 (
#236
b11011111 '
b01010000 (
#238
b01001110 '
b10000011 (
#240
b00000000 '
b10110110 (
#242
b01100000 '
b11101001 (
#244
b11101010 '
b00011100 (
#246
b11100001 '
b01001111 (
#248
b01010001 '
b10000010 (
#250
b00000000 '
b10110101 (
#252
b01011101 '
b11101000 (
#254
b11101000 '
b00011011 (
#256
b11100011 '
b01001110 (
#258
b01010100 '
b10000001 (
#260
b00000000 '
b10110100 (
#262
b00110010 &
b01011010 '
b11100110 (
#264
b00110001 &
b11100101 '
b00010111 (
#266
b00110000 &
b11101010 '
b01000111 (
#268
b00101111 &
b01101001 '
b01110110 (
#270
b00101110 &
b00000011 '
b10100100 (
#272
b00101110 '
b11010010 (
#274
b00101101 &
b10110101 '
b11111111 (
#276
b11111101 '
b00101100 (
#278
b00101100 &
b10111010 '
b01011000 (
#280
b00111000 '
b10000100 (
#282
b00000000 '
b10110000 (
#284
b01001110 '
b11011100 (
#286
b11001111 '
b00001000 (
#288
b11111011 '
b00110100 (
#290
b10100011 '
b01100000 (
#292
b00100101 '
b10001100 (
#294
b00000101 '
b10111000 (
#296
b01100110 '
b11100100 (
#298
b11100001 '
b00010000 (
#300
b11110100 '
b00111100 (
#302
b10001011 '
b01101000 (
#304
b00010101 '
b10010100 (
#306
b00001110 '
b11000000 (
#308
b01111111 '
b11101100 (
#310
b11101111 '
b00011000 (
#312
b11101000 '
b01000100 (
#314
b00101011 &
b01110010 '
b01101111 (
#316
b00001010 '
b10011010 (
#318
b00101010 &
b00011000 '
b11000100 (
#320
b10001011 '
b11101110 (
#322
b00101001 &
b11110001 '
b00010111 (
#324
b00101000 &
b11101010 '
b00111111 (
#326
b10000010 '
b01100111 (
#328
b00010111 '
b10001111 (
#330
b00100111 &
b00001000 '
b10110110 (
#332
b01100000 '
b11011101 (
#334
b00100110 &
b11010001 '
b00000011 (
#336
b11111101 '
b00101001 (
#338
b00100101 &
b11000010 '
b01001110 (
#340
b01010100 '
b01110011 (
#342
b00100100 &
b00000110 '
b10010111 (
#344
b00010011 '
b10111011 (
#346
b01101111 '
b11011111 (
#348
b00100011 &
b11010110 '
b00000010 (
#350
b11111101 '
b00100101 (
#352
b11001101 '
b01001000 (
#354
b01100110 '
b01101011 (
#356
b00010000 '
b10001110 (
#358
b00000111 '
b10110001 (
#360
b01010001 '
b11010100 (
#362
b10111010 '
b11110111 (
#364
b11111010 '
b00011010 (
#366
b11100101 '
b00111101 (
#368
b10001000 '
b01100000 (
#370
b00100101 '
b10000011 (
#372
b00000000 '
b10100110 (
#374
b00110011 '
b11001001 (
#376
b10011010 '
b11101100 (
#378
b11101111 '
b00001111 (
#380
b11110101 '
b00110010 (
#382
b10101001 '
b01010101 (
#384
b01000000 '
b01111000 (
#386
b00000010 '
b10011011 (
#388
b00011010 '
b10111110 (
#390
b00100010 &
b01111000 '
b11100000 (
#392
b11011000 '
b00000010 (
#394
b00100001 &
b11111101 '
b00100011 (
#396
b11010001 '
b01000100 (
#398
b01110010 '
b01100101 (
#400
b00011010 '
b10000110 (
#402
b00011111 &
b00000001 '
b10100101 (
#404
b00011100 &
b00110000 '
b11000001 (
#406
b00011010 &
b10000010 '
b11011011 (
#408
b00011001 &
b11001101 '
b11110100 (
#410
b00011000 &
b11111000 '
b00001100 (
#412
b00100100 (
#414
b11001111 '
b00111100 (
#416
b10001011 '
b01010100 (
#418
b01000011 '
b01101100 (
#420
b00001110 '
b10000100 (
#422
b00000000 '
b10011100 (
#424
b00011100 '
b10110100 (
#426
b01011010 '
b11001100 (
#428
b10100011 '
b11100100 (
#430
b11100001 '
b11111100 (
#432
b11111101 '
b00010100 (
#434
b11101111 '
b00101100 (
#436
b10111010 '
b01000100 (
#438
b01110010 '
b01011100 (
#440
b00101110 '
b01110100 (
#442
b00000101 '
b10001100 (
#444
b10100100 (
#446
b00101110 '
b10111100 (
#448
b01110010 '
b11010100 (
#450
b10111010 '
b11101100 (
#452
b11101111 '
b00000100 (
#454
b11111101 '
b00011100 (
#456
b11100001 '
b00110100 (
#458
b10100011 '
b01001100 (
#460
b01011010 '
b01100100 (
#462
b00010111 &
b00011100 '
b01111011 (
#464
b00000000 '
b10010010 (
#466
b00001100 '
b10101001 (
#468
b00111011 '
b11000000 (
#470
b01111111 '
b11010111 (
#472
b00010101 &
b11000010 '
b11101100 (
#474
b00010011 &
b11101111 '
b11111111 (
#476
b00010010 &
b11111101 '
b00010001 (
#478
b00010001 &
b11110011 '
b00100010 (
#480
b00010000 &
b11010100 '
b00110010 (
#482
b10101001 '
b01000010 (
#484
b01111000 '
b01010010 (
#486
b01001000 '
b01100010 (
#488
b00100000 '
b01110010 (
#490
b00000111 '
b10000010 (
#492
b00000000 '
b10010010 (
#494
b00001100 '
b10100010 (
#496
b00101001 '
b10110010 (
#498
b01010100 '
b11000010 (
#500
b10000101 '
b11010010 (
#502
b10110101 '
b11100010 (
#504
b11011101 '
b11110010 (
#506
b11110110 '
b00000010 (
#508
b11111101 '
b00010010 (
#510
b11110001 '
b00100010 (
#512
b11010100 '
b00110010 (
#514
b10101001 '
b01000010 (
#516
b01111000 '
b01010010 (
#518
b01001000 '
b01100010 (
#520
b00100000 '
b01110010 (
#522
b00000111 '
b10000010 (
#524
b00000000 '
b10010010 (
#526
b00001111 &
b00001100 '
b10100001 (
#528
b00100111 '
b10110000 (
#530
b00001110 &
b01001110 '
b10111110 (
#532
b01111000 '
b11001100 (
#534
b10100011 '
b11011010 (
#536
b00001101 &
b11001010 '
b11100111 (
#538
b00001011 &
b11100110 '
b11110010 (
#540
b00001001 &
b11110110 '
b11111011 (
#542
b00000111 &
b11111101 '
b00000010 (
#544
b00000110 &
b00001000 (
#546
b00000100 &
b11111011 '
b00001100 (
#548
b11111000 '
b00010000 (
#550
b11110100 '
b00010100 (
#552
b11101111 '
b00011000 (
#554
b11101000 '
b00011100 (
#556
b11100001 '
b00100000 (
#558
b11011000 '
b00100100 (
#560
b11001111 '
b00101000 (
#562
b11000101 '
b00101100 (
#564
b10111010 '
b00110000 (
#566
b10101111 '
b00110100 (
#568
b10100011 '
b00111000 (
#570
b10010111 '
b00111100 (
#572
b10001011 '
b01000000 (
#574
b01111110 '
b01000100 (
#576
b01110010 '
b01001000 (
#578
b01100110 '
b01001100 (
#580
b01011010 '
b01010000 (
#582
b01001110 '
b01010100 (
#584
b01000011 '
b01011000 (
#586
b00000011 &
b00111000 '
b01011011 (
#588
b00000010 &
b00110000 '
b01011101 (
#590
b00000001 &
b00101100 '
b01011110 (
#592
b00000000 &
b00101001 '
