task2/rom.sv
module rom #( //# allows for parameterisation so later you can do rom #(ADDRESS_WIDTH=16, DA...=10) (...)
    parameter   ADDRESS_WIDTH = 8,
                DATA_WIDTH = 8
)(
    input logic                         clk,
    input logic     [ADDRESS_WIDTH-1:0] addr1,
    input logic     [ADDRESS_WIDTH-1:0] addr2,
    output logic    [DATA_WIDTH-1:0]    dout1,
    output logic    [DATA_WIDTH-1:0]    dout2
);

logic [DATA_WIDTH-1:0] rom_array [2**ADDRESS_WIDTH-1:0]; //rom_array is an internal value that has memory

initial begin //initial means initialise. Usually non-synthesisable commands (e.g. wouldn't synthesise readmemh, as rom would be built with it)
        $display("Loading rom.");
        //This sort of stuff wouldn't work when programming for an actual chip (other than FPGA, which has data stream)
        $readmemh("sinerom.mem", rom_array);
        //can find more of these macros 
end;

always_ff @(posedge clk) begin
    dout1 <= rom_array[addr1];
    dout2 <= rom_array[addr2];
end;

endmodule

task3/counter.sv
module counter #(
    parameter WIDTH = 8
)(
    // interface signals
    input   logic               clk,    // clock
    input   logic               rst,    // reset
    input   logic               en,
    // input   logic [WIDTH-1:0]   incr,
    output  logic [WIDTH-1:0]   count   // count output 
);

always_ff @ (posedge clk) //this specifies a clocked circuit. posedge rst is async reset.
    if(rst) count <= {WIDTH{1'b0}}; //Uses concatenation operator
    else    count <= count + {{WIDTH-1{1'b0}}, en};

endmodule

task2/sinegen.sv
module sinegen #(
    parameter   A_WIDTH = 8, //Address number
                D_WIDTH = 8 //Length of each word
)(
    //interface signals
    input   logic               clk,
    input   logic               rst,
    input   logic               en,
    input   logic [A_WIDTH-1:0] phase,
    //input   logic [D_WIDTH-1:0] incr,
    output  logic [D_WIDTH-1:0] dout1,
    output  logic [D_WIDTH-1:0] dout2
);

    logic   [A_WIDTH-1:0]       address;    //interconnect wire

counter addrCounter (
    .clk (clk), //These are assigning the values from the module to this module
    .rst (rst),
    .en (en),
    //.incr (incr),
    .count (address)
);

rom sineRom (
    .clk (clk),
    .addr1 (address),
    .addr2 (address + phase), //unsure on the syntax of this
    .dout1 (dout1),
    .dout2 (dout2)
);

endmodule

task2/sinegen.vcd
$version Generated by VerilatedVcd $end
$date Thu Nov  3 18:23:55 2022 $end
$timescale 1ps $end

 $scope module TOP $end
  $var wire  1 # clk $end
  $var wire  8 ' dout1 [7:0] $end
  $var wire  8 ( dout2 [7:0] $end
  $var wire  1 % en $end
  $var wire  8 & phase [7:0] $end
  $var wire  1 $ rst $end
  $scope module sinegen $end
   $var wire 32 + A_WIDTH [31:0] $end
   $var wire 32 + D_WIDTH [31:0] $end
   $var wire  8 ) address [7:0] $end
   $var wire  1 # clk $end
   $var wire  8 ' dout1 [7:0] $end
   $var wire  8 ( dout2 [7:0] $end
   $var wire  1 % en $end
   $var wire  8 & phase [7:0] $end
   $var wire  1 $ rst $end
   $scope module addrCounter $end
    $var wire 32 + WIDTH [31:0] $end
    $var wire  1 # clk $end
    $var wire  8 ) count [7:0] $end
    $var wire  1 % en $end
    $var wire  1 $ rst $end
   $upscope $end
   $scope module sineRom $end
    $var wire 32 + ADDRESS_WIDTH [31:0] $end
    $var wire 32 + DATA_WIDTH [31:0] $end
    $var wire  8 ) addr1 [7:0] $end
    $var wire  8 * addr2 [7:0] $end
    $var wire  1 # clk $end
    $var wire  8 ' dout1 [7:0] $end
    $var wire  8 ( dout2 [7:0] $end
   $upscope $end
  $upscope $end
 $upscope $end
$enddefinitions $end


#0
0#
1$
0%
b00000000 &
b00000000 '
b00000000 (
b00000000 )
b00000000 *
b00000000000000000000000000001000 +
#2
1#
b00110011 &
b11111110 '
b10100110 (
b00110011 *
#4
#6
#8
0$
#10
#12
#14
1%
b00000001 )
b00110100 *
#16
b11111101 '
b10100011 (
b00000010 )
b00110101 *
#18
b10100000 (
b00000011 )
b00110110 *
#20
b10011101 (
b00000100 )
b00110111 *
#22
b10011010 (
b00000101 )
b00111000 *
#24
b10010111 (
b00000110 )
b00111001 *
#26
b11111100 '
b10010100 (
b00000111 )
b00111010 *
#28
b10010001 (
b00001000 )
b00111011 *
#30
b11111011 '
b10001110 (
b00001001 )
b00111100 *
#32
b11111010 '
b10001011 (
b00001010 )
b00111101 *
#34
b10001000 (
b00001011 )
b00111110 *
#36
b11111001 '
b10000101 (
b00001100 )
b00111111 *
#38
b11111000 '
b10000010 (
b00001101 )
b01000000 *
#40
b11110111 '
b01111110 (
b00001110 )
b01000001 *
#42
b11110110 '
b01111011 (
b00001111 )
b01000010 *
#44
b11110101 '
b01111000 (
b00010000 )
b01000011 *
#46
b11110100 '
b01110101 (
b00010001 )
b01000100 *
#48
b11110011 '
b01110010 (
b00010010 )
b01000101 *
#50
b11110001 '
b01101111 (
b00010011 )
b01000110 *
#52
b11110000 '
b01101100 (
b00010100 )
b01000111 *
#54
b11101111 '
b01101001 (
b00010101 )
b01001000 *
#56
b11101101 '
b01100110 (
b00010110 )
b01001001 *
#58
b11101011 '
b01100011 (
b00010111 )
b01001010 *
#60
b11101010 '
b01100000 (
b00011000 )
b01001011 *
#62
b11101000 '
b01011101 (
b00011001 )
b01001100 *
#64
b11100110 '
b01011010 (
b00011010 )
b01001101 *
#66
b11100101 '
b01010111 (
b00011011 )
b01001110 *
#68
b11100011 '
b01010100 (
b00011100 )
b01001111 *
#70
b11100001 '
b01010001 (
b00011101 )
b01010000 *
#72
b11011111 '
b01001110 (
b00011110 )
b01010001 *
#74
b11011101 '
b01001011 (
b00011111 )
b01010010 *
#76
b11011010 '
b01001000 (
b00100000 )
b01010011 *
#78
b11011000 '
b01000101 (
b00100001 )
b01010100 *
#80
b11010110 '
b01000011 (
b00100010 )
b01010101 *
#82
b11010100 '
b01000000 (
b00100011 )
b01010110 *
#84
b11010001 '
b00111101 (
b00100100 )
b01010111 *
#86
b11001111 '
b00111011 (
b00100101 )
b01011000 *
#88
b11001101 '
b00111000 (
b00100110 )
b01011001 *
#90
b11001010 '
b00110101 (
b00100111 )
b01011010 *
#92
b11001000 '
b00110011 (
b00101000 )
b01011011 *
#94
b11000101 '
b00110000 (
b00101001 )
b01011100 *
#96
b11000010 '
b00101110 (
b00101010 )
b01011101 *
#98
b11000000 '
b00101100 (
b00101011 )
b01011110 *
#100
b10111101 '
b00101001 (
b00101100 )
b01011111 *
#102
b10111010 '
b00100111 (
b00101101 )
b01100000 *
#104
b10111000 '
b00100101 (
b00101110 )
b01100001 *
#106
b10110101 '
b00100011 (
b00101111 )
b01100010 *
#108
b10110010 '
b00100000 (
b00110000 )
b01100011 *
#110
b10101111 '
b00011110 (
b00110001 )
b01100100 *
#112
b10101100 '
b00011100 (
b00110010 )
b01100101 *
#114
b10101001 '
b00011010 (
b00110011 )
b01100110 *
#116
b10100110 '
b00011000 (
b00110100 )
b01100111 *
#118
b10100011 '
b00010111 (
b00110101 )
b01101000 *
#120
b10100000 '
b00010101 (
b00110110 )
b01101001 *
#122
b10011101 '
b00010011 (
b00110111 )
b01101010 *
#124
b10011010 '
b00010010 (
b00111000 )
b01101011 *
#126
b10010111 '
b00010000 (
b00111001 )
b01101100 *
#128
b10010100 '
b00001110 (
b00111010 )
b01101101 *
#130
b10010001 '
b00001101 (
b00111011 )
b01101110 *
#132
b10001110 '
b00001100 (
b00111100 )
b01101111 *
#134
b10001011 '
b00001010 (
b00111101 )
b01110000 *
#136
b10001000 '
b00001001 (
b00111110 )
b01110001 *
#138
b10000101 '
b00001000 (
b00111111 )
b01110010 *
#140
b10000010 '
b00000111 (
b01000000 )
b01110011 *
#142
b01111110 '
b00000110 (
b01000001 )
b01110100 *
#144
b01111011 '
b00000101 (
b01000010 )
b01110101 *
#146
b01111000 '
b00000100 (
b01000011 )
b01110110 *
#148
b01110101 '
b00000011 (
b01000100 )
b01110111 *
#150
b01110010 '
b01000101 )
b01111000 *
#152
b01101111 '
b00000010 (
b01000110 )
b01111001 *
#154
b01101100 '
b00000001 (
b01000111 )
b01111010 *
#156
b01101001 '
b01001000 )
b01111011 *
#158
b01100110 '
b00000000 (
b01001001 )
b01111100 *
#160
b01100011 '
b01001010 )
b01111101 *
#162
b01100000 '
b01001011 )
b01111110 *
#164
b01011101 '
b01001100 )
b01111111 *
#166
b00110100 &
b01011010 '
b01001101 )
b10000001 *
#168
b01010111 '
b01001110 )
b10000010 *
#170
b00110101 &
b01010100 '
b01001111 )
b10000100 *
#172
b00110110 &
b01010001 '
b01010000 )
b10000110 *
#174
b00110111 &
b01001110 '
b00000001 (
b01010001 )
b10001000 *
#176
b01001011 '
b00000010 (
b01010010 )
b10001001 *
#178
b01001000 '
b00000011 (
b01010011 )
b10001010 *
#180
b01000101 '
b01010100 )
b10001011 *
#182
b01000011 '
b00000100 (
b01010101 )
b10001100 *
#184
b01000000 '
b00000101 (
b01010110 )
b10001101 *
#186
b00111101 '
b00000110 (
b01010111 )
b10001110 *
#188
b00111011 '
b00000111 (
b01011000 )
b10001111 *
#190
b00111000 '
b00001000 (
b01011001 )
b10010000 *
#192
b00110101 '
b00001001 (
b01011010 )
b10010001 *
#194
b00110011 '
b00001010 (
b01011011 )
b10010010 *
#196
b00110000 '
b00001100 (
b01011100 )
b10010011 *
#198
b00101110 '
b00001101 (
b01011101 )
b10010100 *
#200
b00101100 '
b00001110 (
b01011110 )
b10010101 *
#202
b00101001 '
b00010000 (
b01011111 )
b10010110 *
#204
b00100111 '
b00010010 (
b01100000 )
b10010111 *
#206
b00100101 '
b00010011 (
b01100001 )
b10011000 *
#208
b00100011 '
b00010101 (
b01100010 )
b10011001 *
#210
b00100000 '
b00010111 (
b01100011 )
b10011010 *
#212
b00111000 &
b00011110 '
b00011010 (
b01100100 )
b10011100 *
#214
b00011100 '
b00011100 (
b01100101 )
b10011101 *
#216
b00111001 &
b00011010 '
b00100000 (
b01100110 )
b10011111 *
#218
b00111010 &
b00011000 '
b00100101 (
b01100111 )
b10100001 *
#220
b00111100 &
b00010111 '
b00101100 (
b01101000 )
b10100100 *
#222
b00111110 &
b00010101 '
b00110011 (
b01101001 )
b10100111 *
#224
b00111111 &
b00010011 '
b00111000 (
b01101010 )
b10101001 *
#226
b00010010 '
b00111011 (
b01101011 )
b10101010 *
#228
b00010000 '
b00111101 (
b01101100 )
b10101011 *
#230
b00001110 '
b01000000 (
b01101101 )
b10101100 *
#232
b00001101 '
b01000011 (
b01101110 )
b10101101 *
#234
b00001100 '
b01000101 (
b01101111 )
b10101110 *
#236
b00001010 '
b01001000 (
b01110000 )
b10101111 *
#238
b00001001 '
b01001011 (
b01110001 )
b10110000 *
#240
b00001000 '
b01001110 (
b01110010 )
b10110001 *
#242
b00000111 '
b01010001 (
b01110011 )
b10110010 *
#244
b00000110 '
b01010100 (
b01110100 )
b10110011 *
#246
b00000101 '
b01010111 (
b01110101 )
b10110100 *
#248
b00000100 '
b01011010 (
b01110110 )
b10110101 *
#250
b00000011 '
b01011101 (
b01110111 )
b10110110 *
#252
b01100000 (
b01111000 )
b10110111 *
#254
b00000010 '
b01100011 (
b01111001 )
b10111000 *
#256
b00000001 '
b01100110 (
b01111010 )
b10111001 *
#258
b01101001 (
b01111011 )
b10111010 *
#260
b00000000 '
b01101100 (
b01111100 )
b10111011 *
#262
b01101111 (
b01111101 )
b10111100 *
#264
b01110010 (
b01111110 )
b10111101 *
#266
b01110101 (
b01111111 )
b10111110 *
#268
b01111000 (
b10000000 )
b10111111 *
#270
b01111011 (
b10000001 )
b11000000 *
#272
b01000000 &
b10000010 (
b10000010 )
b11000010 *
#274
b01000001 &
b10001000 (
b10000011 )
b11000100 *
#276
b01000101 &
b10010111 (
b10000100 )
b11001001 *
#278
b01000111 &
b10100000 (
b10000101 )
b11001100 *
#280
b10100011 (
b10000110 )
b11001101 *
#282
b01001000 &
b00000001 '
b10101001 (
b10000111 )
b11001111 *
#284
b10101100 (
b10001000 )
b11010000 *
#286
b00000010 '
b10101111 (
b10001001 )
b11010001 *
#288
b00000011 '
b10110010 (
b10001010 )
b11010010 *
#290
b10110101 (
b10001011 )
b11010011 *
#292
b00000100 '
b10111000 (
b10001100 )
b11010100 *
#294
b00000101 '
b10111010 (
b10001101 )
b11010101 *
#296
b00000110 '
b10111101 (
b10001110 )
b11010110 *
#298
b00000111 '
b11000000 (
b10001111 )
b11010111 *
#300
b00001000 '
b11000010 (
b10010000 )
b11011000 *
#302
b01001001 &
b00001001 '
b11001000 (
b10010001 )
b11011010 *
#304
b01001101 &
b00001010 '
b11010100 (
b10010010 )
b11011111 *
#306
b01010000 &
b00001100 '
b11011101 (
b10010011 )
b11100011 *
#308
b00001101 '
b11011111 (
b10010100 )
b11100100 *
#310
b00001110 '
b11100001 (
b10010101 )
b11100101 *
#312
b00010000 '
b11100011 (
b10010110 )
b11100110 *
#314
b00010010 '
b11100101 (
b10010111 )
b11100111 *
#316
b00010011 '
b11100110 (
b10011000 )
b11101000 *
#318
b00010101 '
b11101000 (
b10011001 )
b11101001 *
#320
b00010111 '
b11101010 (
b10011010 )
b11101010 *
#322
b00011000 '
b11101011 (
b10011011 )
b11101011 *
#324
b00011010 '
b11101101 (
b10011100 )
b11101100 *
#326
b00011100 '
b11101111 (
b10011101 )
b11101101 *
#328
b00011110 '
b11110000 (
b10011110 )
b11101110 *
#330
b00100000 '
b11110001 (
b10011111 )
b11101111 *
#332
b00100011 '
b11110011 (
b10100000 )
b11110000 *
#334
b00100101 '
b11110100 (
b10100001 )
b11110001 *
#336
b00100111 '
b11110101 (
b10100010 )
b11110010 *
#338
b00101001 '
b11110110 (
b10100011 )
b11110011 *
#340
b00101100 '
b11110111 (
b10100100 )
b11110100 *
#342
b00101110 '
b11111000 (
b10100101 )
b11110101 *
#344
b00110000 '
b11111001 (
b10100110 )
b11110110 *
#346
b00110011 '
b11111010 (
b10100111 )
b11110111 *
#348
b00110101 '
b10101000 )
b11111000 *
#350
b00111000 '
b11111011 (
b10101001 )
b11111001 *
#352
b00111011 '
b11111100 (
b10101010 )
b11111010 *
#354
b00111101 '
b10101011 )
b11111011 *
#356
b01000000 '
b11111101 (
b10101100 )
b11111100 *
#358
b01001100 &
b01000011 '
b11111011 (
b10101101 )
b11111001 *
#360
b01001001 &
b01000101 '
b11111010 (
b10101110 )
b11110111 *
#362
b01000101 &
b01001000 '
b11110111 (
b10101111 )
b11110100 *
#364
b01001011 '
b11111000 (
b10110000 )
b11110101 *
#366
b01001110 '
b11111001 (
b10110001 )
b11110110 *
#368
b01010001 '
b11111010 (
b10110010 )
b11110111 *
#370
b01010100 '
b10110011 )
b11111000 *
#372
b01010111 '
b11111011 (
b10110100 )
b11111001 *
#374
b01011010 '
b11111100 (
b10110101 )
b11111010 *
#376
b01011101 '
b10110110 )
b11111011 *
#378
b01100000 '
b11111101 (
b10110111 )
b11111100 *
#380
b01100011 '
b10111000 )
b11111101 *
#382
b01000100 &
b01100110 '
b10111001 )
#384
b01000000 &
b01101001 '
b11111100 (
b10111010 )
b11111010 *
#386
b00111100 &
b01101100 '
b11111010 (
b10111011 )
b11110111 *
#388
b00111010 &
b01101111 '
b11111001 (
b10111100 )
b11110110 *
#390
b01110010 '
b11111010 (
b10111101 )
b11110111 *
#392
b01110101 '
b10111110 )
b11111000 *
#394
b01111000 '
b11111011 (
b10111111 )
b11111001 *
#396
b01111011 '
b11111100 (
b11000000 )
b11111010 *
#398
b01111111 '
b11000001 )
b11111011 *
#400
b10000010 '
b11111101 (
b11000010 )
b11111100 *
#402
b10000101 '
b11000011 )
b11111101 *
#404
b10001000 '
b11000100 )
b11111110 *
#406
b10001011 '
b11000101 )
b11111111 *
#408
b10001110 '
b11000110 )
b00000000 *
#410
b00110111 &
b10010001 '
b11000111 )
b11111110 *
#412
b00110011 &
b10010100 '
b11111100 (
b11001000 )
b11111011 *
#414
b00110000 &
b10010111 '
b11111011 (
b11001001 )
b11111001 *
#416
b00101110 &
b10011010 '
b11111010 (
b11001010 )
b11111000 *
#418
b10011101 '
b11111011 (
b11001011 )
b11111001 *
#420
b10100000 '
b11111100 (
b11001100 )
b11111010 *
#422
b10100011 '
b11001101 )
b11111011 *
#424
b10100110 '
b11111101 (
b11001110 )
b11111100 *
#426
b10101001 '
b11001111 )
b11111101 *
#428
b10101100 '
b11010000 )
b11111110 *
#430
b10101111 '
b11010001 )
b11111111 *
#432
b10110010 '
b11010010 )
b00000000 *
#434
b10110101 '
b11111110 (
b11010011 )
b00000001 *
#436
b10111000 '
b11111101 (
b11010100 )
b00000010 *
#438
b10111010 '
b11010101 )
b00000011 *
#440
b00101101 &
b10111101 '
b11010110 )
#442
b00101001 &
b11000000 '
b11010111 )
b00000000 *
#444
b00101000 &
b11000010 '
b11011000 )
#446
b00100100 &
b11000101 '
b11011001 )
b11111101 *
#448
b11001000 '
b11011010 )
b11111110 *
#450
b11001010 '
b11011011 )
b11111111 *
#452
b11001101 '
b11011100 )
b00000000 *
#454
b11001111 '
b11111110 (
b11011101 )
b00000001 *
#456
b11010001 '
b11111101 (
b11011110 )
b00000010 *
#458
b11010100 '
b11011111 )
b00000011 *
#460
b11010110 '
b11100000 )
b00000100 *
#462
b11011000 '
b11100001 )
b00000101 *
#464
b11011010 '
b11100010 )
b00000110 *
#466
b11011101 '
b11111100 (
b11100011 )
b00000111 *
#468
b11011111 '
b11100100 )
b00001000 *
#470
b11100001 '
b11111011 (
b11100101 )
b00001001 *
#472
b11100011 '
b11111010 (
b11100110 )
b00001010 *
#474
b11100101 '
b11100111 )
b00001011 *
#476
b11100110 '
b11111001 (
b11101000 )
b00001100 *
#478
b11101000 '
b11111000 (
b11101001 )
b00001101 *
#480
b11101010 '
b11110111 (
b11101010 )
b00001110 *
#482
b11101011 '
b11110110 (
b11101011 )
b00001111 *
#484
b11101101 '
b11110101 (
b11101100 )
b00010000 *
#486
b11101111 '
b11110100 (
b11101101 )
b00010001 *
#488
b11110000 '
b11110011 (
b11101110 )
b00010010 *
#490
b11110001 '
b11110001 (
b11101111 )
b00010011 *
#492
b11110011 '
b11110000 (
b11110000 )
b00010100 *
#494
b11110100 '
b11101111 (
b11110001 )
b00010101 *
#496
b11110101 '
b11101101 (
b11110010 )
b00010110 *
#498
b11110110 '
b11101011 (
b11110011 )
b00010111 *
#500
b11110111 '
b11101010 (
b11110100 )
b00011000 *
#502
b11111000 '
b11101000 (
b11110101 )
b00011001 *
#504
b11111001 '
b11100110 (
b11110110 )
b00011010 *
#506
b11111010 '
b11100101 (
b11110111 )
b00011011 *
#508
b11100011 (
b11111000 )
b00011100 *
#510
b11111011 '
b11100001 (
b11111001 )
b00011101 *
#512
b11111100 '
b11011111 (
b11111010 )
b00011110 *
#514
b11011101 (
b11111011 )
b00011111 *
#516
b11111101 '
b11011010 (
b11111100 )
b00100000 *
#518
b11011000 (
b11111101 )
b00100001 *
#520
b11010110 (
b11111110 )
b00100010 *
#522
b11010100 (
b11111111 )
b00100011 *
#524
b11010001 (
b00000000 )
b00100100 *
#526
b11111110 '
b11001111 (
b00000001 )
b00100101 *
#528
b11111101 '
b11001101 (
b00000010 )
b00100110 *
#530
b11001010 (
b00000011 )
b00100111 *
#532
b11001000 (
b00000100 )
b00101000 *
#534
b11000101 (
b00000101 )
b00101001 *
#536
b11000010 (
b00000110 )
b00101010 *
#538
b11111100 '
b11000000 (
b00000111 )
b00101011 *
#540
b10111101 (
b00001000 )
b00101100 *
#542
b11111011 '
b10111010 (
b00001001 )
b00101101 *
#544
b11111010 '
b10111000 (
b00001010 )
b00101110 *
#546
b10110101 (
b00001011 )
b00101111 *
#548
b11111001 '
b10110010 (
b00001100 )
b00110000 *
#550
b11111000 '
b10101111 (
b00001101 )
b00110001 *
#552
b11110111 '
b10101100 (
b00001110 )
b00110010 *
#554
b00100101 &
b11110110 '
b10100110 (
b00001111 )
b00110100 *
#556
b00101011 &
b11110101 '
b10010001 (
b00010000 )
b00111011 *
#558
b00101101 &
b11110100 '
b10001000 (
b00010001 )
b00111110 *
#560
b11110011 '
b10000101 (
b00010010 )
b00111111 *
#562
b11110001 '
b10000010 (
b00010011 )
b01000000 *
#564
b11110000 '
b01111110 (
b00010100 )
b01000001 *
#566
b11101111 '
b01111011 (
b00010101 )
b01000010 *
#568
b11101101 '
b01111000 (
b00010110 )
b01000011 *
#570
b11101011 '
b01110101 (
b00010111 )
b01000100 *
#572
b11101010 '
b01110010 (
b00011000 )
b01000101 *
#574
b11101000 '
b01101111 (
b00011001 )
b01000110 *
#576
b00101110 &
b11100110 '
b01101001 (
b00011010 )
b01001000 *
#578
b00110000 &
b11100101 '
b01100000 (
b00011011 )
b01001011 *
#580
b00110001 &
b11100011 '
b01011010 (
b00011100 )
b01001101 *
#582
b00110011 &
b11100001 '
b01010001 (
b00011101 )
b01010000 *
#584
b00110101 &
b11011111 '
b01001000 (
b00011110 )
b01010011 *
#586
b11011101 '
b01000101 (
b00011111 )
b01010100 *
#588
b11011010 '
b01000011 (
b00100000 )
b01010101 *
#590
b11011000 '
b01000000 (
b00100001 )
b01010110 *
#592
b00110100 &
b11010110 '
b00100010 )
#594
b00110001 &
b11010100 '
b01000101 (
b00100011 )
b01010100 *
#596
b00101100 &
b11010001 '
b01010001 (
b00100100 )
b01010000 *
#598
b11001111 '
b01001110 (
b00100101 )
b01010001 *
#600
b11001101 '
b01001011 (
b00100110 )
b01010010 *
#602
b11001010 '
b01001000 (
b00100111 )
b01010011 *
#604
b11001000 '
b01000101 (
b00101000 )
b01010100 *
#606
b11000101 '
b01000011 (
b00101001 )
b01010101 *
#608
b11000010 '
b01000000 (
b00101010 )
b01010110 *
#610
b11000000 '
b00111101 (
b00101011 )
b01010111 *
#612
b00101001 &
b10111101 '
b01000011 (
b00101100 )
b01010101 *
#614
b00100011 &
b10111010 '
b01010001 (
b00101101 )
b01010000 *
#616
b10111000 '
b01001110 (
b00101110 )
b01010001 *
#618
b10110101 '
b01001011 (
b00101111 )
b01010010 *
#620
b10110010 '
b01001000 (
b00110000 )
b01010011 *
#622
b10101111 '
b01000101 (
b00110001 )
b01010100 *
#624
b10101100 '
b01000011 (
b00110010 )
b01010101 *
#626
b10101001 '
b01000000 (
b00110011 )
b01010110 *
#628
b10100110 '
b00111101 (
b00110100 )
b01010111 *
#630
b00100010 &
b10100011 '
b00110101 )
#632
b00011101 &
b10100000 '
b01001000 (
b00110110 )
b01010011 *
#634
b00011011 &
b10011101 '
b01001011 (
b00110111 )
b01010010 *
#636
b10011010 '
b01001000 (
b00111000 )
b01010011 *
#638
b10010111 '
b01000101 (
b00111001 )
b01010100 *
#640
b10010100 '
b01000011 (
b00111010 )
b01010101 *
#642
b10010001 '
b01000000 (
b00111011 )
b01010110 *
#644
b10001110 '
b00111101 (
b00111100 )
b01010111 *
#646
b10001011 '
b00111011 (
b00111101 )
b01011000 *
#648
b10001000 '
b00111000 (
b00111110 )
b01011001 *
#650
b00011010 &
b10000101 '
b00111111 )
#652
b00010010 &
b10000010 '
b01001011 (
b01000000 )
b01010010 *
#654
b00010001 &
b01111110 '
b01000001 )
#656
b01111011 '
b01001000 (
b01000010 )
b01010011 *
#658
b01111000 '
b01000101 (
b01000011 )
b01010100 *
#660
b01110101 '
b01000011 (
b01000100 )
b01010101 *
#662
b01110010 '
b01000000 (
b01000101 )
b01010110 *
#664
b01101111 '
b00111101 (
b01000110 )
b01010111 *
#666
b01101100 '
b00111011 (
b01000111 )
b01011000 *
#668
b01101001 '
b00111000 (
b01001000 )
b01011001 *
#670
b01100110 '
b00110101 (
b01001001 )
b01011010 *
#672
b01100011 '
b00110011 (
b01001010 )
b01011011 *
#674
b00010000 &
b01100000 '
b01001011 )
#676
b00001011 &
b01011101 '
b00111101 (
b01001100 )
b01010111 *
#678
b00001000 &
b01011010 '
b01000011 (
b01001101 )
b01010101 *
#680
b01010111 '
b01000000 (
b01001110 )
b01010110 *
#682
b01010100 '
b00111101 (
b01001111 )
b01010111 *
#684
b01010001 '
b00111011 (
b01010000 )
b01011000 *
#686
b01001110 '
b00111000 (
b01010001 )
b01011001 *
#688
b01001011 '
b00110101 (
b01010010 )
b01011010 *
#690
b01001000 '
b00110011 (
b01010011 )
b01011011 *
#692
b01000101 '
b00110000 (
b01010100 )
b01011100 *
#694
b01000011 '
b00101110 (
b01010101 )
b01011101 *
#696
b01000000 '
b00101100 (
b01010110 )
b01011110 *
#698
b00111101 '
b00101001 (
b01010111 )
b01011111 *
#700
b00111011 '
b00100111 (
b01011000 )
b01100000 *
#702
b00111000 '
b00100101 (
b01011001 )
b01100001 *
#704
b00110101 '
b00100011 (
b01011010 )
b01100010 *
#706
b00110011 '
b00100000 (
b01011011 )
b01100011 *
#708
b00110000 '
b00011110 (
b01011100 )
b01100100 *
#710
b00101110 '
b00011100 (
b01011101 )
b01100101 *
#712
b00101100 '
b00011010 (
b01011110 )
b01100110 *
#714
b00000111 &
b00101001 '
b01011111 )
#716
b00000110 &
b00100111 '
b01100000 )
#718
b00000101 &
b00100101 '
b01100001 )
#720
b00000100 &
b00100011 '
b01100010 )
#722
b00100000 '
b00011000 (
b01100011 )
b01100111 *
#724
b00011110 '
b00010111 (
b01100100 )
b01101000 *
#726
b00011100 '
b00010101 (
b01100101 )
b01101001 *
#728
b00011010 '
b00010011 (
b01100110 )
b01101010 *
#730
b00011000 '
b00010010 (
b01100111 )
b01101011 *
#732
b00010111 '
b00010000 (
b01101000 )
b01101100 *
#734
b00010101 '
b00001110 (
b01101001 )
b01101101 *
#736
b00010011 '
b00001101 (
b01101010 )
b01101110 *
#738
b00010010 '
b00001100 (
b01101011 )
b01101111 *
#740
b00010000 '
b00001010 (
b01101100 )
b01110000 *
#742
b00001110 '
b00001001 (
b01101101 )
b01110001 *
#744
b00000011 &
b00001101 '
b01101110 )
#746
b00000001 &
b00001100 '
b00001010 (
b01101111 )
b01110000 *
#748
b00000000 &
b00001010 '
b01110000 )
#750
b00001001 '
b00001001 (
b01110001 )
b01110001 *
#752
b00001000 '
b00001000 (
b01110010 )
b01110010 *
#754
b00000111 '
b00000111 (
b01110011 )
b01110011 *
#756
b00000110 '
b00000110 (
b01110100 )
b01110100 *
#758
b00000101 '
b00000101 (
b01110101 )
b01110101 *
#760
b00000100 '
b00000100 (
b01110110 )
b01110110 *
#762
b00000011 '
b00000011 (
b01110111 )
b01110111 *
#764
b01111000 )
b01111000 *
#766
b00000010 '
b00000010 (
b01111001 )
b01111001 *
#768
b00000001 '
b00000001 (
b01111010 )
b01111010 *
#770
b01111011 )
b01111011 *
#772
b00000000 '
b00000000 (
b01111100 )
b01111100 *
#774
b01111101 )
b01111101 *
#776
b01111110 )
b01111110 *
#778
b01111111 )
b01111111 *
#780
b10000000 )
b10000000 *
#782
b10000001 )
b10000001 *
#784
b10000010 )
b10000010 *
#786
b10000011 )
b10000011 *
#788
b10000100 )
b10000100 *
#790
b10000101 )
b10000101 *
#792
b10000110 )
b10000110 *
#794
b00000001 '
b00000001 (
b10000111 )
b10000111 *
#796
b10001000 )
b10001000 *
#798
b00000010 '
b00000010 (
b10001001 )
b10001001 *
#800
b00000011 '
b00000011 (
b10001010 )
b10001010 *
#802
b10001011 )
b10001011 *
#804
b00000100 '
b00000100 (
b10001100 )
b10001100 *
#806
b00000101 '
b00000101 (
b10001101 )
b10001101 *
#808
b00000110 '
b00000110 (
b10001110 )
b10001110 *
#810
b00000111 '
b00000111 (
b10001111 )
b10001111 *
#812
b00001000 '
b00001000 (
b10010000 )
b10010000 *
#814
b00001001 '
b00001001 (
b10010001 )
b10010001 *
#816
b00001010 '
b00001010 (
b10010010 )
b10010010 *
#818
b00001100 '
b00001100 (
b10010011 )
b10010011 *
#820
b00001101 '
b00001101 (
b10010100 )
b10010100 *
#822
b00001110 '
b00001110 (
b10010101 )
b10010101 *
#824
b00010000 '
b00010000 (
b10010110 )
b10010110 *
#826
b00010010 '
b00010010 (
b10010111 )
b10010111 *
#828
b00010011 '
b00010011 (
b10011000 )
b10011000 *
#830
b00010101 '
b00010101 (
b10011001 )
b10011001 *
#832
b00010111 '
b00010111 (
b10011010 )
b10011010 *
#834
b00011000 '
b00011000 (
b10011011 )
b10011011 *
#836
b00011010 '
b00011010 (
b10011100 )
b10011100 *
#838
b00011100 '
b00011100 (
b10011101 )
b10011101 *
#840
b00011110 '
b00011110 (
b10011110 )
b10011110 *
#842
b00100000 '
b00100000 (
b10011111 )
b10011111 *
#844
b00100011 '
b00100011 (
b10100000 )
b10100000 *
#846
b00100101 '
b00100101 (
b10100001 )
b10100001 *
#848
b00100111 '
b00100111 (
b10100010 )
b10100010 *
#850
b00101001 '
b00101001 (
b10100011 )
b10100011 *
#852
b00101100 '
b00101100 (
b10100100 )
b10100100 *
#854
b00101110 '
b00101110 (
b10100101 )
b10100101 *
#856
b00110000 '
b00110000 (
b10100110 )
b10100110 *
#858
b00110011 '
b00110011 (
b10100111 )
b10100111 *
#860
b00110101 '
b00110101 (
b10101000 )
b10101000 *
#862
b00111000 '
b00111000 (
b10101001 )
b10101001 *
#864
b00111011 '
b00111011 (
b10101010 )
b10101010 *
#866
b00111101 '
b00111101 (
b10101011 )
b10101011 *
#868
b01000000 '
b01000000 (
b10101100 )
b10101100 *
#870
b01000011 '
b01000011 (
b10101101 )
b10101101 *
#872
b01000101 '
b01000101 (
b10101110 )
b10101110 *
#874
b01001000 '
b01001000 (
b10101111 )
b10101111 *
#876
b01001011 '
b01001011 (
b10110000 )
b10110000 *
#878
b01001110 '
b01001110 (
b10110001 )
b10110001 *
#880
b01010001 '
b01010001 (
b10110010 )
b10110010 *
#882
b01010100 '
b01010100 (
b10110011 )
b10110011 *
#884
b01010111 '
b01010111 (
b10110100 )
b10110100 *
#886
b01011010 '
b01011010 (
b10110101 )
b10110101 *
#888
b01011101 '
b01011101 (
b10110110 )
b10110110 *
#890
b01100000 '
b01100000 (
b10110111 )
b10110111 *
